complexheart/__init__.py
complexheart/domainmodel/__init__.py
complexheart/domainmodel/invariants.py
complexheart-0.0.1.dist-info/LICENSE
complexheart-0.0.1.dist-info/METADATA
complexheart-0.0.1.dist-info/WHEEL
complexheart-0.0.1.dist-info/top_level.txt
complexheart-0.0.1.dist-info/RECORD
